lc_dir/__init__.py
lc_dir/cli.py
lc_dir-0.1.16.dist-info/entry_points.txt
lc_dir-0.1.16.dist-info/LICENSE
lc_dir-0.1.16.dist-info/METADATA
lc_dir-0.1.16.dist-info/WHEEL
lc_dir-0.1.16.dist-info/RECORD
