Metadata-Version: 2.3
Name: lc-dir
Version: 0.1.16
Summary: Copy all non-git-ignored files from any subdirectory into llm-context for LLM consumption
License: MIT
Keywords: llm,cli,python,context,ai
Author: Aviad Rozenhek [aviar1@gmail.com](mailto:aviar1@gmail.com)
Requires-Python: >=3.10
Classifier: License :: OSI Approved :: MIT License
Classifier: Programming Language :: Python :: 3
Classifier: Programming Language :: Python :: 3.10
Classifier: Programming Language :: Python :: 3.11
Classifier: Programming Language :: Python :: 3.12
Classifier: Programming Language :: Python :: 3.13
Requires-Dist: colorama (>=0.4.6,<0.5.0)
Requires-Dist: llm-context (>=0.3.2,<0.4.0)
Project-URL: Repository, https://github.com/aviadr1/lc-dir
